{
  "date": "2026-05-03",
  "snapshots": [
    {
      "t": "2026-05-03T14:16:18Z",
      "pitchers": {
        "Joe Ryan": {
          "k_line": 5.5,
          "DraftKings": {
            "over": 106,
            "under": -135
          },
          "Kalshi": {
            "over": 109,
            "under": -154
          }
        },
        "Trey Yesavage": {
          "k_line": 4.5,
          "DraftKings": {
            "over": -161,
            "under": 126
          },
          "Kalshi": {
            "over": -126,
            "under": 105
          }
        },
        "Zack Littell": {
          "k_line": 3.5,
          "DraftKings": {
            "over": 102,
            "under": -130
          },
          "BetMGM": {
            "over": -118,
            "under": -110
          },
          "Kalshi": {
            "over": 105,
            "under": -126
          }
        },
        "Max Fried": {
          "k_line": 5.5,
          "DraftKings": {
            "over": -148,
            "under": 116
          },
          "BetMGM": {
            "over": -155,
            "under": 115
          },
          "FanDuel": {
            "over": -144,
            "under": 108
          },
          "Kalshi": {
            "over": -137,
            "under": 101
          }
        },
        "Ranger Suarez": {
          "k_line": 4.5,
          "DraftKings": {
            "over": -125,
            "under": -102
          },
          "BetMGM": {
            "over": -120,
            "under": -110
          }
        },
        "Braxton Ashcraft": {
          "k_line": 5.5,
          "DraftKings": {
            "over": -133,
            "under": 104
          },
          "BetMGM": {
            "over": -140,
            "under": 105
          },
          "Kalshi": {
            "over": -121,
            "under": 101
          }
        },
        "Chase Burns": {
          "k_line": 6.5,
          "DraftKings": {
            "over": -123,
            "under": -104
          },
          "BetMGM": {
            "over": -110,
            "under": -120
          },
          "Kalshi": {
            "over": -131,
            "under": 109
          }
        },
        "Jesus Luzardo": {
          "k_line": 6.5,
          "DraftKings": {
            "over": -116,
            "under": -110
          },
          "BetMGM": {
            "over": 105,
            "under": -140
          },
          "Kalshi": {
            "over": -103,
            "under": -116
          }
        },
        "Chris Paddack": {
          "k_line": 4.5,
          "BetMGM": {
            "over": 125,
            "under": -165
          },
          "Kalshi": {
            "over": 159,
            "under": -191
          }
        },
        "Tyler Mahle": {
          "k_line": 3.5,
          "DraftKings": {
            "over": -161,
            "under": 126
          },
          "BetMGM": {
            "over": -160,
            "under": 120
          },
          "Kalshi": {
            "over": -175,
            "under": 114
          }
        },
        "Steven Matz": {
          "k_line": 4.5,
          "DraftKings": {
            "over": 106,
            "under": -135
          },
          "BetMGM": {
            "over": 105,
            "under": -140
          },
          "Kalshi": {
            "over": 105,
            "under": -137
          }
        },
        "Dustin May": {
          "k_line": 4.5,
          "DraftKings": {
            "over": 125,
            "under": -160
          },
          "BetMGM": {
            "over": 110,
            "under": -150
          },
          "Kalshi": {
            "over": 114,
            "under": -137
          }
        },
        "Justin Wrobleski": {
          "k_line": 3.5,
          "DraftKings": {
            "over": -141,
            "under": 110
          },
          "BetMGM": {
            "over": -160,
            "under": 120
          },
          "Kalshi": {
            "over": -142,
            "under": 119
          }
        },
        "Merrill Kelly": {
          "k_line": 3.5,
          "DraftKings": {
            "over": -159,
            "under": 125
          },
          "BetMGM": {
            "over": -155,
            "under": 115
          },
          "Kalshi": {
            "over": -148,
            "under": 124
          }
        },
        "Matthew Boyd": {
          "k_line": 3.5,
          "BetMGM": {
            "over": -210,
            "under": 155
          },
          "Kalshi": {
            "over": -218,
            "under": 152
          }
        },
        "Spencer Strider": {
          "k_line": 5.5,
          "DraftKings": {
            "over": -102,
            "under": -125
          },
          "BetMGM": {
            "over": -110,
            "under": -120
          },
          "Kalshi": {
            "over": 119,
            "under": -161
          }
        },
        "Kyle Freeland": {
          "k_line": 3.5,
          "DraftKings": {
            "over": -144,
            "under": 113
          },
          "BetMGM": {
            "over": -135,
            "under": 100
          },
          "Kalshi": {
            "over": -131,
            "under": 101
          }
        },
        "Aaron Civale": {
          "k_line": 4.5,
          "DraftKings": {
            "over": 125,
            "under": -160
          },
          "BetMGM": {
            "over": 120,
            "under": -160
          }
        },
        "Parker Messick": {
          "k_line": 4.5,
          "BetMGM": {
            "over": -200,
            "under": 145
          }
        },
        "Jack Kochanowicz": {
          "k_line": 3.5,
          "DraftKings": {
            "over": -116,
            "under": -110
          },
          "BetMGM": {
            "over": -125,
            "under": -105
          },
          "Kalshi": {
            "over": -112,
            "under": -107
          }
        },
        "Clay Holmes": {
          "k_line": 4.5,
          "DraftKings": {
            "over": -142,
            "under": 111
          },
          "BetMGM": {
            "over": -135,
            "under": 100
          },
          "Kalshi": {
            "over": -137,
            "under": 114
          }
        },
        "Kris Bubic": {
          "k_line": 5.5,
          "DraftKings": {
            "over": 101,
            "under": -129
          },
          "BetMGM": {
            "over": -105,
            "under": -130
          },
          "Kalshi": {
            "over": 101,
            "under": -126
          }
        },
        "Luis Castillo": {
          "k_line": 4.5,
          "DraftKings": {
            "over": -127,
            "under": 100
          },
          "BetMGM": {
            "over": -120,
            "under": -110
          },
          "Kalshi": {
            "over": -116,
            "under": -103
          }
        },
        "Anthony Kay": {
          "k_line": 3.5,
          "DraftKings": {
            "over": 110,
            "under": -140
          },
          "BetMGM": {
            "over": -105,
            "under": -125
          }
        },
        "Jack Leiter": {
          "k_line": 5.5,
          "DraftKings": {
            "over": 118,
            "under": -151
          },
          "BetMGM": {
            "over": 100,
            "under": -135
          },
          "Kalshi": {
            "over": 124,
            "under": -148
          }
        }
      }
    }
  ],
  "archive_dates": [
    "2026-05-03"
  ],
  "updated_at": "2026-05-03T14:16:18Z"
}