{
  "date": "2026-04-30",
  "snapshots": [
    {
      "t": "2026-04-30T15:24:06Z",
      "pitchers": {
        "Bryce Elder": {
          "k_line": 4.5,
          "BetMGM": {
            "over": -150,
            "under": 110
          },
          "Kalshi": {
            "over": -131,
            "under": 105
          }
        },
        "Framber Valdez": {
          "k_line": 4.5,
          "BetMGM": {
            "over": -110,
            "under": -120
          },
          "Kalshi": {
            "over": -107,
            "under": -112
          }
        },
        "Cristopher Sanchez": {
          "k_line": 6.5,
          "BetMGM": {
            "over": -105,
            "under": -125
          },
          "Kalshi": {
            "over": 124,
            "under": -148
          }
        },
        "Logan Webb": {
          "k_line": 5.5,
          "BetMGM": {
            "over": 115,
            "under": -155
          },
          "Kalshi": {
            "over": -103,
            "under": -131
          }
        },
        "Paul Skenes": {
          "k_line": 6.5,
          "BetMGM": {
            "over": -135,
            "under": 100
          },
          "Kalshi": {
            "over": -121,
            "under": 101
          }
        },
        "Hunter Dobbins": {
          "k_line": 3.5,
          "BetMGM": {
            "over": -115,
            "under": -115
          }
        },
        "Andrew Abbott": {
          "k_line": 4.5,
          "BetMGM": {
            "over": -150,
            "under": 110
          },
          "Kalshi": {
            "over": -154,
            "under": 129
          }
        },
        "Michael Lorenzen": {
          "k_line": 4.5,
          "BetMGM": {
            "over": 110,
            "under": -150
          },
          "Kalshi": {
            "over": 119,
            "under": -142
          }
        },
        "Freddy Peralta": {
          "k_line": 5.5,
          "BetMGM": {
            "over": -130,
            "under": -105
          },
          "Kalshi": {
            "over": -116,
            "under": -107
          }
        },
        "Miles Mikolas": {
          "k_line": 3.5,
          "Kalshi": {
            "over": 101,
            "under": -121
          }
        },
        "Michael Soroka": {
          "k_line": 5.5,
          "BetMGM": {
            "over": -120,
            "under": -110
          }
        },
        "Brandon Woodruff": {
          "k_line": 4.5,
          "Kalshi": {
            "over": -168,
            "under": 129
          }
        },
        "Noah Cameron": {
          "k_line": 4.5,
          "BetMGM": {
            "over": -115,
            "under": -115
          }
        },
        "Bailey Ober": {
          "k_line": 3.5,
          "Kalshi": {
            "over": -148,
            "under": 114
          }
        },
        "Kevin Gausman": {
          "k_line": 5.5,
          "Kalshi": {
            "over": -112,
            "under": -112
          }
        }
      }
    },
    {
      "t": "2026-04-30T16:28:50Z",
      "pitchers": {
        "Framber Valdez": {
          "k_line": 4.5,
          "BetMGM": {
            "over": -110,
            "under": -120
          },
          "Kalshi": {
            "over": -107,
            "under": -112
          }
        },
        "Bryce Elder": {
          "k_line": 4.5,
          "BetMGM": {
            "over": -150,
            "under": 110
          },
          "Kalshi": {
            "over": -131,
            "under": 105
          }
        },
        "Cristopher Sanchez": {
          "k_line": 6.5,
          "BetMGM": {
            "over": -105,
            "under": -125
          },
          "Kalshi": {
            "over": 119,
            "under": -154
          }
        },
        "Logan Webb": {
          "k_line": 5.5,
          "BetMGM": {
            "over": 115,
            "under": -155
          },
          "Kalshi": {
            "over": 105,
            "under": -137
          }
        },
        "Paul Skenes": {
          "k_line": 6.5,
          "BetMGM": {
            "over": -140,
            "under": 105
          },
          "Kalshi": {
            "over": -121,
            "under": 101
          }
        },
        "Hunter Dobbins": {
          "k_line": 3.5,
          "BetMGM": {
            "over": -115,
            "under": -115
          },
          "Kalshi": {
            "over": -112,
            "under": -107
          }
        },
        "Peter Lambert": {
          "k_line": 5.5,
          "BetMGM": {
            "over": 120,
            "under": -160
          },
          "Kalshi": {
            "over": 152,
            "under": -218
          }
        },
        "Chris Bassitt": {
          "k_line": 3.5,
          "Kalshi": {
            "over": -175,
            "under": 124
          }
        },
        "Andrew Abbott": {
          "k_line": 4.5,
          "BetMGM": {
            "over": -160,
            "under": 120
          },
          "Kalshi": {
            "over": -161,
            "under": 114
          }
        },
        "Michael Lorenzen": {
          "k_line": 4.5,
          "BetMGM": {
            "over": 110,
            "under": -150
          }
        },
        "Freddy Peralta": {
          "k_line": 5.5,
          "BetMGM": {
            "over": -150,
            "under": 110
          },
          "Kalshi": {
            "over": -131,
            "under": 101
          }
        },
        "Miles Mikolas": {
          "k_line": 3.5,
          "Kalshi": {
            "over": 114,
            "under": -137
          }
        },
        "Michael Soroka": {
          "k_line": 5.5,
          "BetMGM": {
            "over": -135,
            "under": 100
          },
          "Kalshi": {
            "over": -131,
            "under": 105
          }
        },
        "Brandon Woodruff": {
          "k_line": 4.5,
          "Kalshi": {
            "over": -161,
            "under": 124
          }
        },
        "Noah Cameron": {
          "k_line": 4.5,
          "BetMGM": {
            "over": -115,
            "under": -115
          }
        },
        "Bailey Ober": {
          "k_line": 3.5,
          "Kalshi": {
            "over": -148,
            "under": 124
          }
        },
        "Kevin Gausman": {
          "k_line": 5.5,
          "BetMGM": {
            "over": -110,
            "under": -120
          },
          "Kalshi": {
            "over": -116,
            "under": -107
          }
        }
      }
    },
    {
      "t": "2026-04-30T16:39:27Z",
      "pitchers": {
        "Paul Skenes": {
          "k_line": 6.5,
          "BetMGM": {
            "over": -140,
            "under": 105
          },
          "Kalshi": {
            "over": -121,
            "under": 101
          }
        },
        "Chris Bassitt": {
          "k_line": 3.5,
          "Kalshi": {
            "over": -175,
            "under": 124
          }
        },
        "Framber Valdez": {
          "k_line": 4.5,
          "BetMGM": {
            "over": -110,
            "under": -120
          },
          "Kalshi": {
            "over": -107,
            "under": -112
          }
        },
        "Logan Webb": {
          "k_line": 5.5,
          "BetMGM": {
            "over": 115,
            "under": -155
          },
          "Kalshi": {
            "over": 105,
            "under": -137
          }
        },
        "Hunter Dobbins": {
          "k_line": 3.5,
          "BetMGM": {
            "over": -115,
            "under": -115
          },
          "Kalshi": {
            "over": -112,
            "under": -107
          }
        },
        "Cristopher Sanchez": {
          "k_line": 6.5,
          "BetMGM": {
            "over": -105,
            "under": -125
          },
          "Kalshi": {
            "over": 119,
            "under": -154
          }
        },
        "Bryce Elder": {
          "k_line": 4.5,
          "BetMGM": {
            "over": -150,
            "under": 110
          },
          "Kalshi": {
            "over": -131,
            "under": 105
          }
        },
        "Peter Lambert": {
          "k_line": 5.5,
          "BetMGM": {
            "over": 120,
            "under": -160
          },
          "Kalshi": {
            "over": 152,
            "under": -218
          }
        },
        "Andrew Abbott": {
          "k_line": 4.5,
          "BetMGM": {
            "over": -160,
            "under": 120
          }
        },
        "Michael Lorenzen": {
          "k_line": 4.5,
          "BetMGM": {
            "over": 110,
            "under": -150
          },
          "Kalshi": {
            "over": 119,
            "under": -161
          }
        },
        "Freddy Peralta": {
          "k_line": 5.5,
          "BetMGM": {
            "over": -150,
            "under": 110
          },
          "Kalshi": {
            "over": -131,
            "under": 101
          }
        },
        "Miles Mikolas": {
          "k_line": 3.5,
          "Kalshi": {
            "over": 114,
            "under": -137
          }
        },
        "Michael Soroka": {
          "k_line": 5.5,
          "BetMGM": {
            "over": -135,
            "under": 100
          },
          "Kalshi": {
            "over": -131,
            "under": 105
          }
        },
        "Brandon Woodruff": {
          "k_line": 4.5,
          "Kalshi": {
            "over": -161,
            "under": 124
          }
        },
        "Noah Cameron": {
          "k_line": 4.5,
          "BetMGM": {
            "over": -115,
            "under": -115
          }
        },
        "Jeffrey Springs": {
          "k_line": 3.5,
          "BetMGM": {
            "over": -165,
            "under": 125
          }
        },
        "Bailey Ober": {
          "k_line": 3.5,
          "Kalshi": {
            "over": -148,
            "under": 124
          }
        },
        "Kevin Gausman": {
          "k_line": 5.5,
          "BetMGM": {
            "over": -110,
            "under": -120
          }
        }
      }
    },
    {
      "t": "2026-04-30T16:45:00Z",
      "pitchers": {
        "Paul Skenes": {
          "k_line": 6.5,
          "BetMGM": {
            "over": -140,
            "under": 105
          },
          "Kalshi": {
            "over": -121,
            "under": 101
          }
        },
        "Michael Lorenzen": {
          "k_line": 4.5,
          "BetMGM": {
            "over": 110,
            "under": -150
          },
          "Kalshi": {
            "over": 119,
            "under": -161
          }
        },
        "Cristopher Sanchez": {
          "k_line": 6.5,
          "BetMGM": {
            "over": -105,
            "under": -125
          },
          "Kalshi": {
            "over": 119,
            "under": -154
          }
        },
        "Logan Webb": {
          "k_line": 5.5,
          "BetMGM": {
            "over": 115,
            "under": -155
          },
          "Kalshi": {
            "over": 105,
            "under": -137
          }
        },
        "Bryce Elder": {
          "k_line": 4.5,
          "BetMGM": {
            "over": -150,
            "under": 110
          },
          "Kalshi": {
            "over": -131,
            "under": 105
          }
        },
        "Chris Bassitt": {
          "k_line": 3.5,
          "Kalshi": {
            "over": -175,
            "under": 124
          }
        },
        "Peter Lambert": {
          "k_line": 5.5,
          "BetMGM": {
            "over": 120,
            "under": -160
          },
          "Kalshi": {
            "over": 152,
            "under": -218
          }
        },
        "Framber Valdez": {
          "k_line": 4.5,
          "BetMGM": {
            "over": -110,
            "under": -120
          },
          "Kalshi": {
            "over": -107,
            "under": -112
          }
        },
        "Hunter Dobbins": {
          "k_line": 3.5,
          "BetMGM": {
            "over": -115,
            "under": -115
          },
          "Kalshi": {
            "over": -112,
            "under": -107
          }
        },
        "Andrew Abbott": {
          "k_line": 4.5,
          "BetMGM": {
            "over": -160,
            "under": 120
          }
        },
        "Freddy Peralta": {
          "k_line": 5.5,
          "BetMGM": {
            "over": -150,
            "under": 110
          },
          "Kalshi": {
            "over": -126,
            "under": 101
          }
        },
        "Miles Mikolas": {
          "k_line": 3.5,
          "Kalshi": {
            "over": 114,
            "under": -137
          }
        },
        "Michael Soroka": {
          "k_line": 5.5,
          "BetMGM": {
            "over": -135,
            "under": 100
          },
          "Kalshi": {
            "over": -131,
            "under": 105
          }
        },
        "Brandon Woodruff": {
          "k_line": 4.5,
          "Kalshi": {
            "over": -161,
            "under": 124
          }
        },
        "Noah Cameron": {
          "k_line": 4.5,
          "BetMGM": {
            "over": -115,
            "under": -115
          }
        },
        "Jeffrey Springs": {
          "k_line": 3.5,
          "BetMGM": {
            "over": -165,
            "under": 125
          }
        },
        "Bailey Ober": {
          "k_line": 3.5,
          "Kalshi": {
            "over": -154,
            "under": 124
          }
        },
        "Kevin Gausman": {
          "k_line": 5.5,
          "BetMGM": {
            "over": -110,
            "under": -120
          },
          "Kalshi": {
            "over": -112,
            "under": -107
          }
        }
      }
    },
    {
      "t": "2026-04-30T17:03:45Z",
      "pitchers": {
        "Chris Bassitt": {
          "k_line": 3.5,
          "Kalshi": {
            "over": -175,
            "under": 124
          }
        },
        "Framber Valdez": {
          "k_line": 4.5,
          "BetMGM": {
            "over": -110,
            "under": -120
          },
          "Kalshi": {
            "over": -107,
            "under": -112
          }
        },
        "Hunter Dobbins": {
          "k_line": 3.5,
          "BetMGM": {
            "over": -115,
            "under": -115
          },
          "Kalshi": {
            "over": -112,
            "under": -107
          }
        },
        "Andrew Abbott": {
          "k_line": 4.5,
          "BetMGM": {
            "over": -160,
            "under": 120
          }
        },
        "Cristopher Sanchez": {
          "k_line": 6.5,
          "BetMGM": {
            "over": -105,
            "under": -125
          },
          "Kalshi": {
            "over": 119,
            "under": -154
          }
        },
        "Bryce Elder": {
          "k_line": 4.5,
          "BetMGM": {
            "over": -150,
            "under": 110
          },
          "Kalshi": {
            "over": -131,
            "under": 105
          }
        },
        "Michael Lorenzen": {
          "k_line": 4.5,
          "BetMGM": {
            "over": 110,
            "under": -150
          },
          "Kalshi": {
            "over": 119,
            "under": -161
          }
        },
        "Logan Webb": {
          "k_line": 5.5,
          "BetMGM": {
            "over": 115,
            "under": -155
          },
          "Kalshi": {
            "over": 105,
            "under": -137
          }
        },
        "Peter Lambert": {
          "k_line": 5.5,
          "BetMGM": {
            "over": 120,
            "under": -160
          },
          "Kalshi": {
            "over": 152,
            "under": -218
          }
        },
        "Paul Skenes": {
          "k_line": 6.5,
          "BetMGM": {
            "over": -140,
            "under": 105
          },
          "Kalshi": {
            "over": -121,
            "under": 101
          }
        },
        "Freddy Peralta": {
          "k_line": 5.5,
          "Kalshi": {
            "over": -126,
            "under": 105
          }
        },
        "Miles Mikolas": {
          "k_line": 3.5,
          "Kalshi": {
            "over": 129,
            "under": -154
          }
        },
        "Michael Soroka": {
          "k_line": 5.5,
          "BetMGM": {
            "over": -135,
            "under": 100
          },
          "Kalshi": {
            "over": -131,
            "under": 105
          }
        },
        "Brandon Woodruff": {
          "k_line": 4.5,
          "Kalshi": {
            "over": -154,
            "under": 124
          }
        },
        "Noah Cameron": {
          "k_line": 4.5,
          "BetMGM": {
            "over": -115,
            "under": -115
          }
        },
        "Jeffrey Springs": {
          "k_line": 3.5,
          "BetMGM": {
            "over": -165,
            "under": 125
          }
        },
        "Bailey Ober": {
          "k_line": 3.5,
          "Kalshi": {
            "over": -154,
            "under": 124
          }
        },
        "Kevin Gausman": {
          "k_line": 5.5,
          "BetMGM": {
            "over": -110,
            "under": -120
          },
          "Kalshi": {
            "over": -112,
            "under": -107
          }
        }
      }
    },
    {
      "t": "2026-04-30T17:40:10Z",
      "pitchers": {
        "Bryce Elder": {
          "k_line": 4.5,
          "BetMGM": {
            "over": -150,
            "under": 110
          },
          "Kalshi": {
            "over": -131,
            "under": 105
          }
        },
        "Michael Lorenzen": {
          "k_line": 4.5,
          "BetMGM": {
            "over": 110,
            "under": -150
          },
          "Kalshi": {
            "over": 119,
            "under": -161
          }
        },
        "Andrew Abbott": {
          "k_line": 4.5,
          "BetMGM": {
            "over": -160,
            "under": 120
          }
        },
        "Freddy Peralta": {
          "k_line": 5.5,
          "Kalshi": {
            "over": -126,
            "under": 105
          }
        },
        "Framber Valdez": {
          "k_line": 4.5,
          "BetMGM": {
            "over": -110,
            "under": -120
          },
          "Kalshi": {
            "over": -107,
            "under": -112
          }
        },
        "Michael Soroka": {
          "k_line": 5.5,
          "BetMGM": {
            "over": -135,
            "under": 100
          },
          "Kalshi": {
            "over": -131,
            "under": 105
          }
        },
        "Chris Bassitt": {
          "k_line": 3.5,
          "Kalshi": {
            "over": -175,
            "under": 124
          }
        },
        "Logan Webb": {
          "k_line": 5.5,
          "BetMGM": {
            "over": 115,
            "under": -155
          },
          "Kalshi": {
            "over": 105,
            "under": -137
          }
        },
        "Hunter Dobbins": {
          "k_line": 3.5,
          "BetMGM": {
            "over": -115,
            "under": -115
          },
          "Kalshi": {
            "over": -112,
            "under": -107
          }
        },
        "Miles Mikolas": {
          "k_line": 3.5,
          "Kalshi": {
            "over": 129,
            "under": -154
          }
        },
        "Brandon Woodruff": {
          "k_line": 4.5,
          "Kalshi": {
            "over": -154,
            "under": 124
          }
        },
        "Paul Skenes": {
          "k_line": 6.5,
          "BetMGM": {
            "over": -140,
            "under": 105
          },
          "Kalshi": {
            "over": -121,
            "under": 101
          }
        },
        "Cristopher Sanchez": {
          "k_line": 6.5,
          "BetMGM": {
            "over": -105,
            "under": -125
          },
          "Kalshi": {
            "over": 119,
            "under": -154
          }
        },
        "Peter Lambert": {
          "k_line": 5.5,
          "BetMGM": {
            "over": 120,
            "under": -160
          },
          "Kalshi": {
            "over": 152,
            "under": -218
          }
        },
        "Noah Cameron": {
          "k_line": 4.5,
          "BetMGM": {
            "over": -115,
            "under": -115
          }
        },
        "Jeffrey Springs": {
          "k_line": 3.5,
          "BetMGM": {
            "over": -165,
            "under": 125
          }
        },
        "Bailey Ober": {
          "k_line": 3.5,
          "Kalshi": {
            "over": -154,
            "under": 129
          }
        },
        "Kevin Gausman": {
          "k_line": 5.5,
          "BetMGM": {
            "over": -110,
            "under": -120
          },
          "Kalshi": {
            "over": -112,
            "under": -107
          }
        }
      }
    },
    {
      "t": "2026-04-30T17:53:48Z",
      "pitchers": {
        "Cristopher Sanchez": {
          "k_line": 6.5,
          "BetMGM": {
            "over": -105,
            "under": -125
          },
          "Kalshi": {
            "over": 119,
            "under": -154
          }
        },
        "Michael Lorenzen": {
          "k_line": 4.5,
          "BetMGM": {
            "over": 110,
            "under": -150
          },
          "Kalshi": {
            "over": 119,
            "under": -161
          }
        },
        "Michael Soroka": {
          "k_line": 5.5,
          "BetMGM": {
            "over": -135,
            "under": 100
          },
          "Kalshi": {
            "over": -131,
            "under": 105
          }
        },
        "Peter Lambert": {
          "k_line": 5.5,
          "BetMGM": {
            "over": 120,
            "under": -160
          },
          "Kalshi": {
            "over": 152,
            "under": -218
          }
        },
        "Paul Skenes": {
          "k_line": 6.5,
          "BetMGM": {
            "over": -140,
            "under": 105
          },
          "Kalshi": {
            "over": -121,
            "under": 101
          }
        },
        "Logan Webb": {
          "k_line": 5.5,
          "BetMGM": {
            "over": 115,
            "under": -155
          },
          "Kalshi": {
            "over": 105,
            "under": -137
          }
        },
        "Andrew Abbott": {
          "k_line": 4.5,
          "BetMGM": {
            "over": -160,
            "under": 120
          }
        },
        "Chris Bassitt": {
          "k_line": 3.5,
          "Kalshi": {
            "over": -175,
            "under": 124
          }
        },
        "Framber Valdez": {
          "k_line": 4.5,
          "BetMGM": {
            "over": -110,
            "under": -120
          },
          "Kalshi": {
            "over": -107,
            "under": -112
          }
        },
        "Hunter Dobbins": {
          "k_line": 3.5,
          "BetMGM": {
            "over": -115,
            "under": -115
          },
          "Kalshi": {
            "over": -112,
            "under": -107
          }
        },
        "Brandon Woodruff": {
          "k_line": 4.5,
          "Kalshi": {
            "over": -154,
            "under": 124
          }
        },
        "Bryce Elder": {
          "k_line": 4.5,
          "BetMGM": {
            "over": -150,
            "under": 110
          },
          "Kalshi": {
            "over": -131,
            "under": 105
          }
        },
        "Freddy Peralta": {
          "k_line": 5.5,
          "Kalshi": {
            "over": -126,
            "under": 105
          }
        },
        "Miles Mikolas": {
          "k_line": 3.5,
          "Kalshi": {
            "over": 129,
            "under": -154
          }
        },
        "Noah Cameron": {
          "k_line": 4.5,
          "BetMGM": {
            "over": -115,
            "under": -115
          }
        },
        "Jeffrey Springs": {
          "k_line": 3.5,
          "BetMGM": {
            "over": -165,
            "under": 125
          }
        },
        "Bailey Ober": {
          "k_line": 3.5,
          "Kalshi": {
            "over": -154,
            "under": 129
          }
        },
        "Kevin Gausman": {
          "k_line": 5.5,
          "BetMGM": {
            "over": -110,
            "under": -120
          },
          "Kalshi": {
            "over": -112,
            "under": -107
          }
        }
      }
    },
    {
      "t": "2026-04-30T18:16:56Z",
      "pitchers": {
        "Freddy Peralta": {
          "k_line": 5.5,
          "Kalshi": {
            "over": -126,
            "under": 105
          }
        },
        "Chris Bassitt": {
          "k_line": 3.5,
          "Kalshi": {
            "over": -175,
            "under": 124
          }
        },
        "Michael Soroka": {
          "k_line": 5.5,
          "BetMGM": {
            "over": -135,
            "under": 100
          },
          "Kalshi": {
            "over": -131,
            "under": 105
          }
        },
        "Hunter Dobbins": {
          "k_line": 3.5,
          "BetMGM": {
            "over": -115,
            "under": -115
          },
          "Kalshi": {
            "over": -112,
            "under": -107
          }
        },
        "Framber Valdez": {
          "k_line": 4.5,
          "BetMGM": {
            "over": -110,
            "under": -120
          },
          "Kalshi": {
            "over": -107,
            "under": -112
          }
        },
        "Michael Lorenzen": {
          "k_line": 4.5,
          "BetMGM": {
            "over": 110,
            "under": -150
          },
          "Kalshi": {
            "over": 119,
            "under": -161
          }
        },
        "Miles Mikolas": {
          "k_line": 3.5,
          "Kalshi": {
            "over": 129,
            "under": -154
          }
        },
        "Brandon Woodruff": {
          "k_line": 4.5,
          "Kalshi": {
            "over": -154,
            "under": 124
          }
        },
        "Paul Skenes": {
          "k_line": 6.5,
          "BetMGM": {
            "over": -140,
            "under": 105
          },
          "Kalshi": {
            "over": -121,
            "under": 101
          }
        },
        "Cristopher Sanchez": {
          "k_line": 6.5,
          "BetMGM": {
            "over": -105,
            "under": -125
          },
          "Kalshi": {
            "over": 119,
            "under": -154
          }
        },
        "Bryce Elder": {
          "k_line": 4.5,
          "BetMGM": {
            "over": -150,
            "under": 110
          },
          "Kalshi": {
            "over": -131,
            "under": 105
          }
        },
        "Andrew Abbott": {
          "k_line": 4.5,
          "BetMGM": {
            "over": -160,
            "under": 120
          }
        },
        "Logan Webb": {
          "k_line": 5.5,
          "BetMGM": {
            "over": 115,
            "under": -155
          },
          "Kalshi": {
            "over": 105,
            "under": -137
          }
        },
        "Peter Lambert": {
          "k_line": 5.5,
          "BetMGM": {
            "over": 120,
            "under": -160
          },
          "Kalshi": {
            "over": 152,
            "under": -218
          }
        },
        "Noah Cameron": {
          "k_line": 4.5,
          "BetMGM": {
            "over": -115,
            "under": -115
          }
        },
        "Jeffrey Springs": {
          "k_line": 3.5,
          "BetMGM": {
            "over": -175,
            "under": 130
          }
        },
        "Bailey Ober": {
          "k_line": 3.5,
          "Kalshi": {
            "over": -154,
            "under": 129
          }
        },
        "Kevin Gausman": {
          "k_line": 5.5,
          "BetMGM": {
            "over": -110,
            "under": -120
          },
          "Kalshi": {
            "over": -112,
            "under": -107
          }
        }
      }
    },
    {
      "t": "2026-04-30T18:55:04Z",
      "pitchers": {
        "Michael Soroka": {
          "k_line": 5.5,
          "BetMGM": {
            "over": -135,
            "under": 100
          },
          "Kalshi": {
            "over": -131,
            "under": 105
          }
        },
        "Framber Valdez": {
          "k_line": 4.5,
          "BetMGM": {
            "over": -110,
            "under": -120
          },
          "Kalshi": {
            "over": -107,
            "under": -112
          }
        },
        "Freddy Peralta": {
          "k_line": 5.5,
          "Kalshi": {
            "over": -126,
            "under": 105
          }
        },
        "Miles Mikolas": {
          "k_line": 3.5,
          "Kalshi": {
            "over": 129,
            "under": -154
          }
        },
        "Peter Lambert": {
          "k_line": 5.5,
          "BetMGM": {
            "over": 120,
            "under": -160
          },
          "Kalshi": {
            "over": 152,
            "under": -218
          }
        },
        "Michael Lorenzen": {
          "k_line": 4.5,
          "BetMGM": {
            "over": 110,
            "under": -150
          },
          "Kalshi": {
            "over": 119,
            "under": -161
          }
        },
        "Chris Bassitt": {
          "k_line": 3.5,
          "Kalshi": {
            "over": -175,
            "under": 124
          }
        },
        "Andrew Abbott": {
          "k_line": 4.5,
          "BetMGM": {
            "over": -160,
            "under": 120
          }
        },
        "Paul Skenes": {
          "k_line": 6.5,
          "BetMGM": {
            "over": -140,
            "under": 105
          },
          "Kalshi": {
            "over": -121,
            "under": 101
          }
        },
        "Brandon Woodruff": {
          "k_line": 4.5,
          "Kalshi": {
            "over": -154,
            "under": 124
          }
        },
        "Cristopher Sanchez": {
          "k_line": 6.5,
          "BetMGM": {
            "over": -105,
            "under": -125
          },
          "Kalshi": {
            "over": 119,
            "under": -154
          }
        },
        "Hunter Dobbins": {
          "k_line": 3.5,
          "BetMGM": {
            "over": -115,
            "under": -115
          },
          "Kalshi": {
            "over": -112,
            "under": -107
          }
        },
        "Bryce Elder": {
          "k_line": 4.5,
          "BetMGM": {
            "over": -150,
            "under": 110
          },
          "Kalshi": {
            "over": -131,
            "under": 105
          }
        },
        "Logan Webb": {
          "k_line": 5.5,
          "BetMGM": {
            "over": 115,
            "under": -155
          },
          "Kalshi": {
            "over": 105,
            "under": -137
          }
        },
        "Noah Cameron": {
          "k_line": 4.5,
          "BetMGM": {
            "over": -115,
            "under": -115
          }
        },
        "Jeffrey Springs": {
          "k_line": 3.5,
          "BetMGM": {
            "over": -175,
            "under": 130
          }
        },
        "Bailey Ober": {
          "k_line": 3.5,
          "Kalshi": {
            "over": -154,
            "under": 129
          }
        },
        "Kevin Gausman": {
          "k_line": 5.5,
          "BetMGM": {
            "over": -110,
            "under": -120
          },
          "Kalshi": {
            "over": -112,
            "under": -107
          }
        }
      }
    },
    {
      "t": "2026-04-30T19:47:26Z",
      "pitchers": {
        "Andrew Abbott": {
          "k_line": 4.5,
          "BetMGM": {
            "over": -160,
            "under": 120
          }
        },
        "Bryce Elder": {
          "k_line": 4.5,
          "BetMGM": {
            "over": -150,
            "under": 110
          },
          "Kalshi": {
            "over": -131,
            "under": 105
          }
        },
        "Cristopher Sanchez": {
          "k_line": 6.5,
          "BetMGM": {
            "over": -105,
            "under": -125
          },
          "Kalshi": {
            "over": 119,
            "under": -154
          }
        },
        "Chris Bassitt": {
          "k_line": 3.5,
          "Kalshi": {
            "over": -175,
            "under": 124
          }
        },
        "Michael Lorenzen": {
          "k_line": 4.5,
          "BetMGM": {
            "over": 110,
            "under": -150
          },
          "Kalshi": {
            "over": 119,
            "under": -161
          }
        },
        "Miles Mikolas": {
          "k_line": 3.5,
          "Kalshi": {
            "over": 129,
            "under": -154
          }
        },
        "Peter Lambert": {
          "k_line": 5.5,
          "BetMGM": {
            "over": 120,
            "under": -160
          },
          "Kalshi": {
            "over": 152,
            "under": -218
          }
        },
        "Paul Skenes": {
          "k_line": 6.5,
          "BetMGM": {
            "over": -140,
            "under": 105
          },
          "Kalshi": {
            "over": -121,
            "under": 101
          }
        },
        "Brandon Woodruff": {
          "k_line": 4.5,
          "Kalshi": {
            "over": -154,
            "under": 124
          }
        },
        "Jeffrey Springs": {
          "k_line": 3.5,
          "BetMGM": {
            "over": -175,
            "under": 130
          }
        },
        "Logan Webb": {
          "k_line": 5.5,
          "BetMGM": {
            "over": 115,
            "under": -155
          },
          "Kalshi": {
            "over": 105,
            "under": -137
          }
        },
        "Hunter Dobbins": {
          "k_line": 3.5,
          "BetMGM": {
            "over": -115,
            "under": -115
          },
          "Kalshi": {
            "over": -112,
            "under": -107
          }
        },
        "Freddy Peralta": {
          "k_line": 5.5,
          "Kalshi": {
            "over": -126,
            "under": 105
          }
        },
        "Noah Cameron": {
          "k_line": 4.5,
          "BetMGM": {
            "over": -115,
            "under": -115
          }
        },
        "Michael Soroka": {
          "k_line": 5.5,
          "BetMGM": {
            "over": -135,
            "under": 100
          },
          "Kalshi": {
            "over": -131,
            "under": 105
          }
        },
        "Framber Valdez": {
          "k_line": 4.5,
          "BetMGM": {
            "over": -110,
            "under": -120
          },
          "Kalshi": {
            "over": -107,
            "under": -112
          }
        },
        "Bailey Ober": {
          "k_line": 3.5,
          "Kalshi": {
            "over": -154,
            "under": 129
          }
        },
        "Kevin Gausman": {
          "k_line": 5.5,
          "BetMGM": {
            "over": -110,
            "under": -120
          },
          "Kalshi": {
            "over": -112,
            "under": -107
          }
        }
      }
    },
    {
      "t": "2026-04-30T19:59:53Z",
      "pitchers": {
        "Logan Webb": {
          "k_line": 5.5,
          "BetMGM": {
            "over": 115,
            "under": -155
          },
          "Kalshi": {
            "over": 105,
            "under": -137
          }
        },
        "Noah Cameron": {
          "k_line": 4.5,
          "BetMGM": {
            "over": -115,
            "under": -115
          }
        },
        "Chris Bassitt": {
          "k_line": 3.5,
          "Kalshi": {
            "over": -175,
            "under": 124
          }
        },
        "Miles Mikolas": {
          "k_line": 3.5,
          "Kalshi": {
            "over": 129,
            "under": -154
          }
        },
        "Bryce Elder": {
          "k_line": 4.5,
          "BetMGM": {
            "over": -150,
            "under": 110
          },
          "Kalshi": {
            "over": -131,
            "under": 105
          }
        },
        "Andrew Abbott": {
          "k_line": 4.5,
          "BetMGM": {
            "over": -160,
            "under": 120
          }
        },
        "Michael Lorenzen": {
          "k_line": 4.5,
          "BetMGM": {
            "over": 110,
            "under": -150
          },
          "Kalshi": {
            "over": 119,
            "under": -161
          }
        },
        "Cristopher Sanchez": {
          "k_line": 6.5,
          "BetMGM": {
            "over": -105,
            "under": -125
          },
          "Kalshi": {
            "over": 119,
            "under": -154
          }
        },
        "Jeffrey Springs": {
          "k_line": 3.5,
          "BetMGM": {
            "over": -175,
            "under": 130
          }
        },
        "Paul Skenes": {
          "k_line": 6.5,
          "BetMGM": {
            "over": -140,
            "under": 105
          },
          "Kalshi": {
            "over": -121,
            "under": 101
          }
        },
        "Framber Valdez": {
          "k_line": 4.5,
          "BetMGM": {
            "over": -110,
            "under": -120
          },
          "Kalshi": {
            "over": -107,
            "under": -112
          }
        },
        "Michael Soroka": {
          "k_line": 5.5,
          "BetMGM": {
            "over": -135,
            "under": 100
          },
          "Kalshi": {
            "over": -131,
            "under": 105
          }
        },
        "Peter Lambert": {
          "k_line": 5.5,
          "BetMGM": {
            "over": 120,
            "under": -160
          },
          "Kalshi": {
            "over": 152,
            "under": -218
          }
        },
        "Hunter Dobbins": {
          "k_line": 3.5,
          "BetMGM": {
            "over": -115,
            "under": -115
          },
          "Kalshi": {
            "over": -112,
            "under": -107
          }
        },
        "Brandon Woodruff": {
          "k_line": 4.5,
          "Kalshi": {
            "over": -154,
            "under": 124
          }
        },
        "Freddy Peralta": {
          "k_line": 5.5,
          "Kalshi": {
            "over": -126,
            "under": 105
          }
        },
        "Bailey Ober": {
          "k_line": 3.5,
          "Kalshi": {
            "over": -154,
            "under": 129
          }
        },
        "Kevin Gausman": {
          "k_line": 5.5,
          "BetMGM": {
            "over": -110,
            "under": -120
          },
          "Kalshi": {
            "over": -112,
            "under": -107
          }
        }
      }
    },
    {
      "t": "2026-04-30T20:14:36Z",
      "pitchers": {
        "Peter Lambert": {
          "k_line": 5.5,
          "BetMGM": {
            "over": 120,
            "under": -160
          },
          "Kalshi": {
            "over": 152,
            "under": -218
          }
        },
        "Jeffrey Springs": {
          "k_line": 3.5,
          "BetMGM": {
            "over": -175,
            "under": 130
          }
        },
        "Michael Lorenzen": {
          "k_line": 4.5,
          "BetMGM": {
            "over": 110,
            "under": -150
          },
          "Kalshi": {
            "over": 119,
            "under": -161
          }
        },
        "Michael Soroka": {
          "k_line": 5.5,
          "BetMGM": {
            "over": -135,
            "under": 100
          },
          "Kalshi": {
            "over": -131,
            "under": 105
          }
        },
        "Logan Webb": {
          "k_line": 5.5,
          "BetMGM": {
            "over": 115,
            "under": -155
          },
          "Kalshi": {
            "over": 105,
            "under": -137
          }
        },
        "Brandon Woodruff": {
          "k_line": 4.5,
          "Kalshi": {
            "over": -154,
            "under": 124
          }
        },
        "Paul Skenes": {
          "k_line": 6.5,
          "BetMGM": {
            "over": -140,
            "under": 105
          },
          "Kalshi": {
            "over": -121,
            "under": 101
          }
        },
        "Framber Valdez": {
          "k_line": 4.5,
          "BetMGM": {
            "over": -110,
            "under": -120
          },
          "Kalshi": {
            "over": -107,
            "under": -112
          }
        },
        "Hunter Dobbins": {
          "k_line": 3.5,
          "BetMGM": {
            "over": -115,
            "under": -115
          },
          "Kalshi": {
            "over": -112,
            "under": -107
          }
        },
        "Chris Bassitt": {
          "k_line": 3.5,
          "Kalshi": {
            "over": -175,
            "under": 124
          }
        },
        "Freddy Peralta": {
          "k_line": 5.5,
          "Kalshi": {
            "over": -126,
            "under": 105
          }
        },
        "Andrew Abbott": {
          "k_line": 4.5,
          "BetMGM": {
            "over": -160,
            "under": 120
          }
        },
        "Cristopher Sanchez": {
          "k_line": 6.5,
          "BetMGM": {
            "over": -105,
            "under": -125
          },
          "Kalshi": {
            "over": 119,
            "under": -154
          }
        },
        "Miles Mikolas": {
          "k_line": 3.5,
          "Kalshi": {
            "over": 129,
            "under": -154
          }
        },
        "Noah Cameron": {
          "k_line": 4.5,
          "BetMGM": {
            "over": -115,
            "under": -115
          }
        },
        "Bryce Elder": {
          "k_line": 4.5,
          "BetMGM": {
            "over": -150,
            "under": 110
          },
          "Kalshi": {
            "over": -131,
            "under": 105
          }
        },
        "Bailey Ober": {
          "k_line": 3.5,
          "Kalshi": {
            "over": -154,
            "under": 129
          }
        },
        "Kevin Gausman": {
          "k_line": 5.5,
          "BetMGM": {
            "over": 115,
            "under": -155
          },
          "Kalshi": {
            "over": -112,
            "under": -107
          }
        }
      }
    },
    {
      "t": "2026-04-30T20:42:54Z",
      "pitchers": {
        "Paul Skenes": {
          "k_line": 6.5,
          "BetMGM": {
            "over": -140,
            "under": 105
          },
          "Kalshi": {
            "over": -121,
            "under": 101
          }
        },
        "Jeffrey Springs": {
          "k_line": 3.5,
          "BetMGM": {
            "over": -175,
            "under": 130
          }
        },
        "Michael Lorenzen": {
          "k_line": 4.5,
          "BetMGM": {
            "over": 110,
            "under": -150
          },
          "Kalshi": {
            "over": 119,
            "under": -161
          }
        },
        "Andrew Abbott": {
          "k_line": 4.5,
          "BetMGM": {
            "over": -160,
            "under": 120
          }
        },
        "Cristopher Sanchez": {
          "k_line": 6.5,
          "BetMGM": {
            "over": -105,
            "under": -125
          },
          "Kalshi": {
            "over": 119,
            "under": -154
          }
        },
        "Peter Lambert": {
          "k_line": 5.5,
          "BetMGM": {
            "over": 120,
            "under": -160
          },
          "Kalshi": {
            "over": 152,
            "under": -218
          }
        },
        "Hunter Dobbins": {
          "k_line": 3.5,
          "BetMGM": {
            "over": -115,
            "under": -115
          },
          "Kalshi": {
            "over": -112,
            "under": -107
          }
        },
        "Freddy Peralta": {
          "k_line": 5.5,
          "Kalshi": {
            "over": -126,
            "under": 105
          }
        },
        "Bryce Elder": {
          "k_line": 4.5,
          "BetMGM": {
            "over": -150,
            "under": 110
          },
          "Kalshi": {
            "over": -131,
            "under": 105
          }
        },
        "Framber Valdez": {
          "k_line": 4.5,
          "BetMGM": {
            "over": -110,
            "under": -120
          },
          "Kalshi": {
            "over": -107,
            "under": -112
          }
        },
        "Chris Bassitt": {
          "k_line": 3.5,
          "Kalshi": {
            "over": -175,
            "under": 124
          }
        },
        "Miles Mikolas": {
          "k_line": 3.5,
          "Kalshi": {
            "over": 129,
            "under": -154
          }
        },
        "Michael Soroka": {
          "k_line": 5.5,
          "BetMGM": {
            "over": -135,
            "under": 100
          },
          "Kalshi": {
            "over": -131,
            "under": 105
          }
        },
        "Brandon Woodruff": {
          "k_line": 4.5,
          "Kalshi": {
            "over": -154,
            "under": 124
          }
        },
        "Noah Cameron": {
          "k_line": 4.5,
          "BetMGM": {
            "over": -115,
            "under": -115
          }
        },
        "Logan Webb": {
          "k_line": 5.5,
          "BetMGM": {
            "over": 115,
            "under": -155
          },
          "Kalshi": {
            "over": 105,
            "under": -137
          }
        },
        "Bailey Ober": {
          "k_line": 3.5,
          "BetMGM": {
            "over": -165,
            "under": 125
          },
          "Kalshi": {
            "over": -154,
            "under": 129
          }
        },
        "Kevin Gausman": {
          "k_line": 5.5,
          "BetMGM": {
            "over": 105,
            "under": -140
          },
          "Kalshi": {
            "over": 114,
            "under": -137
          }
        }
      }
    },
    {
      "t": "2026-04-30T21:14:37Z",
      "pitchers": {
        "Chris Bassitt": {
          "k_line": 3.5,
          "Kalshi": {
            "over": -175,
            "under": 124
          }
        },
        "Miles Mikolas": {
          "k_line": 3.5,
          "Kalshi": {
            "over": 129,
            "under": -154
          }
        },
        "Logan Webb": {
          "k_line": 5.5,
          "BetMGM": {
            "over": 115,
            "under": -155
          },
          "Kalshi": {
            "over": 105,
            "under": -137
          }
        },
        "Jeffrey Springs": {
          "k_line": 3.5,
          "BetMGM": {
            "over": -175,
            "under": 130
          }
        },
        "Hunter Dobbins": {
          "k_line": 3.5,
          "BetMGM": {
            "over": -115,
            "under": -115
          },
          "Kalshi": {
            "over": -112,
            "under": -107
          }
        },
        "Noah Cameron": {
          "k_line": 4.5,
          "BetMGM": {
            "over": -115,
            "under": -115
          }
        },
        "Freddy Peralta": {
          "k_line": 5.5,
          "Kalshi": {
            "over": -126,
            "under": 105
          }
        },
        "Paul Skenes": {
          "k_line": 6.5,
          "BetMGM": {
            "over": -140,
            "under": 105
          },
          "Kalshi": {
            "over": -121,
            "under": 101
          }
        },
        "Framber Valdez": {
          "k_line": 4.5,
          "BetMGM": {
            "over": -110,
            "under": -120
          },
          "Kalshi": {
            "over": -107,
            "under": -112
          }
        },
        "Michael Lorenzen": {
          "k_line": 4.5,
          "BetMGM": {
            "over": 110,
            "under": -150
          },
          "Kalshi": {
            "over": 119,
            "under": -161
          }
        },
        "Cristopher Sanchez": {
          "k_line": 6.5,
          "BetMGM": {
            "over": -105,
            "under": -125
          },
          "Kalshi": {
            "over": 119,
            "under": -154
          }
        },
        "Peter Lambert": {
          "k_line": 5.5,
          "BetMGM": {
            "over": 120,
            "under": -160
          },
          "Kalshi": {
            "over": 152,
            "under": -218
          }
        },
        "Andrew Abbott": {
          "k_line": 4.5,
          "BetMGM": {
            "over": -160,
            "under": 120
          }
        },
        "Michael Soroka": {
          "k_line": 5.5,
          "BetMGM": {
            "over": -135,
            "under": 100
          },
          "Kalshi": {
            "over": -131,
            "under": 105
          }
        },
        "Brandon Woodruff": {
          "k_line": 4.5,
          "Kalshi": {
            "over": -154,
            "under": 124
          }
        },
        "Bryce Elder": {
          "k_line": 4.5,
          "BetMGM": {
            "over": -150,
            "under": 110
          },
          "Kalshi": {
            "over": -131,
            "under": 105
          }
        },
        "Bailey Ober": {
          "k_line": 3.5,
          "BetMGM": {
            "over": -165,
            "under": 125
          },
          "Kalshi": {
            "over": -154,
            "under": 129
          }
        },
        "Kevin Gausman": {
          "k_line": 5.5,
          "BetMGM": {
            "over": 105,
            "under": -140
          },
          "Kalshi": {
            "over": 119,
            "under": -142
          }
        }
      }
    },
    {
      "t": "2026-04-30T21:34:46Z",
      "pitchers": {
        "Michael Lorenzen": {
          "k_line": 4.5,
          "BetMGM": {
            "over": 110,
            "under": -150
          },
          "Kalshi": {
            "over": 119,
            "under": -161
          }
        },
        "Brandon Woodruff": {
          "k_line": 4.5,
          "Kalshi": {
            "over": -154,
            "under": 124
          }
        },
        "Noah Cameron": {
          "k_line": 4.5,
          "BetMGM": {
            "over": -115,
            "under": -115
          }
        },
        "Bryce Elder": {
          "k_line": 4.5,
          "BetMGM": {
            "over": -150,
            "under": 110
          },
          "Kalshi": {
            "over": -131,
            "under": 105
          }
        },
        "Peter Lambert": {
          "k_line": 5.5,
          "BetMGM": {
            "over": 120,
            "under": -160
          },
          "Kalshi": {
            "over": 152,
            "under": -218
          }
        },
        "Cristopher Sanchez": {
          "k_line": 6.5,
          "BetMGM": {
            "over": -105,
            "under": -125
          },
          "Kalshi": {
            "over": 119,
            "under": -154
          }
        },
        "Logan Webb": {
          "k_line": 5.5,
          "BetMGM": {
            "over": 115,
            "under": -155
          },
          "Kalshi": {
            "over": 105,
            "under": -137
          }
        },
        "Freddy Peralta": {
          "k_line": 5.5,
          "Kalshi": {
            "over": -126,
            "under": 105
          }
        },
        "Miles Mikolas": {
          "k_line": 3.5,
          "Kalshi": {
            "over": 129,
            "under": -154
          }
        },
        "Hunter Dobbins": {
          "k_line": 3.5,
          "BetMGM": {
            "over": -115,
            "under": -115
          },
          "Kalshi": {
            "over": -112,
            "under": -107
          }
        },
        "Paul Skenes": {
          "k_line": 6.5,
          "BetMGM": {
            "over": -140,
            "under": 105
          },
          "Kalshi": {
            "over": -121,
            "under": 101
          }
        },
        "Framber Valdez": {
          "k_line": 4.5,
          "BetMGM": {
            "over": -110,
            "under": -120
          },
          "Kalshi": {
            "over": -107,
            "under": -112
          }
        },
        "Andrew Abbott": {
          "k_line": 4.5,
          "BetMGM": {
            "over": -160,
            "under": 120
          }
        },
        "Michael Soroka": {
          "k_line": 5.5,
          "BetMGM": {
            "over": -135,
            "under": 100
          },
          "Kalshi": {
            "over": -131,
            "under": 105
          }
        },
        "Chris Bassitt": {
          "k_line": 3.5,
          "Kalshi": {
            "over": -175,
            "under": 124
          }
        },
        "Jeffrey Springs": {
          "k_line": 3.5,
          "BetMGM": {
            "over": -175,
            "under": 130
          }
        },
        "Bailey Ober": {
          "k_line": 3.5,
          "BetMGM": {
            "over": -165,
            "under": 125
          },
          "Kalshi": {
            "over": -154,
            "under": 124
          }
        },
        "Kevin Gausman": {
          "k_line": 5.5,
          "BetMGM": {
            "over": 105,
            "under": -140
          },
          "Kalshi": {
            "over": 119,
            "under": -142
          }
        }
      }
    },
    {
      "t": "2026-04-30T22:08:07Z",
      "pitchers": {
        "Brandon Woodruff": {
          "k_line": 4.5,
          "Kalshi": {
            "over": -154,
            "under": 124
          }
        },
        "Cristopher Sanchez": {
          "k_line": 6.5,
          "BetMGM": {
            "over": -105,
            "under": -125
          },
          "Kalshi": {
            "over": 119,
            "under": -154
          }
        },
        "Noah Cameron": {
          "k_line": 4.5,
          "BetMGM": {
            "over": -115,
            "under": -115
          }
        },
        "Peter Lambert": {
          "k_line": 5.5,
          "BetMGM": {
            "over": 120,
            "under": -160
          },
          "Kalshi": {
            "over": 152,
            "under": -218
          }
        },
        "Paul Skenes": {
          "k_line": 6.5,
          "BetMGM": {
            "over": -140,
            "under": 105
          },
          "Kalshi": {
            "over": -121,
            "under": 101
          }
        },
        "Framber Valdez": {
          "k_line": 4.5,
          "BetMGM": {
            "over": -110,
            "under": -120
          },
          "Kalshi": {
            "over": -107,
            "under": -112
          }
        },
        "Logan Webb": {
          "k_line": 5.5,
          "BetMGM": {
            "over": 115,
            "under": -155
          },
          "Kalshi": {
            "over": 105,
            "under": -137
          }
        },
        "Michael Lorenzen": {
          "k_line": 4.5,
          "BetMGM": {
            "over": 110,
            "under": -150
          },
          "Kalshi": {
            "over": 119,
            "under": -161
          }
        },
        "Freddy Peralta": {
          "k_line": 5.5,
          "Kalshi": {
            "over": -126,
            "under": 105
          }
        },
        "Jeffrey Springs": {
          "k_line": 3.5,
          "BetMGM": {
            "over": -175,
            "under": 130
          }
        },
        "Hunter Dobbins": {
          "k_line": 3.5,
          "BetMGM": {
            "over": -115,
            "under": -115
          },
          "Kalshi": {
            "over": -112,
            "under": -107
          }
        },
        "Chris Bassitt": {
          "k_line": 3.5,
          "Kalshi": {
            "over": -175,
            "under": 124
          }
        },
        "Bryce Elder": {
          "k_line": 4.5,
          "BetMGM": {
            "over": -150,
            "under": 110
          },
          "Kalshi": {
            "over": -131,
            "under": 105
          }
        },
        "Andrew Abbott": {
          "k_line": 4.5,
          "BetMGM": {
            "over": -160,
            "under": 120
          }
        },
        "Michael Soroka": {
          "k_line": 5.5,
          "BetMGM": {
            "over": -135,
            "under": 100
          },
          "Kalshi": {
            "over": -131,
            "under": 105
          }
        },
        "Miles Mikolas": {
          "k_line": 3.5,
          "Kalshi": {
            "over": 129,
            "under": -154
          }
        },
        "Bailey Ober": {
          "k_line": 3.5,
          "BetMGM": {
            "over": -165,
            "under": 125
          },
          "Kalshi": {
            "over": -154,
            "under": 124
          }
        },
        "Kevin Gausman": {
          "k_line": 5.5,
          "BetMGM": {
            "over": 105,
            "under": -140
          },
          "Kalshi": {
            "over": 119,
            "under": -142
          }
        }
      }
    },
    {
      "t": "2026-04-30T22:30:16Z",
      "pitchers": {
        "Peter Lambert": {
          "k_line": 5.5,
          "BetMGM": {
            "over": 120,
            "under": -160
          },
          "Kalshi": {
            "over": 152,
            "under": -218
          }
        },
        "Noah Cameron": {
          "k_line": 4.5,
          "BetMGM": {
            "over": -115,
            "under": -115
          }
        },
        "Framber Valdez": {
          "k_line": 4.5,
          "BetMGM": {
            "over": -110,
            "under": -120
          },
          "Kalshi": {
            "over": -107,
            "under": -112
          }
        },
        "Cristopher Sanchez": {
          "k_line": 6.5,
          "BetMGM": {
            "over": -105,
            "under": -125
          },
          "Kalshi": {
            "over": 119,
            "under": -154
          }
        },
        "Logan Webb": {
          "k_line": 5.5,
          "BetMGM": {
            "over": 115,
            "under": -155
          },
          "Kalshi": {
            "over": 105,
            "under": -137
          }
        },
        "Andrew Abbott": {
          "k_line": 4.5,
          "BetMGM": {
            "over": -160,
            "under": 120
          }
        },
        "Michael Soroka": {
          "k_line": 5.5,
          "BetMGM": {
            "over": -135,
            "under": 100
          },
          "Kalshi": {
            "over": -131,
            "under": 105
          }
        },
        "Miles Mikolas": {
          "k_line": 3.5,
          "Kalshi": {
            "over": 129,
            "under": -154
          }
        },
        "Brandon Woodruff": {
          "k_line": 4.5,
          "Kalshi": {
            "over": -154,
            "under": 124
          }
        },
        "Hunter Dobbins": {
          "k_line": 3.5,
          "BetMGM": {
            "over": -115,
            "under": -115
          },
          "Kalshi": {
            "over": -112,
            "under": -107
          }
        },
        "Bryce Elder": {
          "k_line": 4.5,
          "BetMGM": {
            "over": -150,
            "under": 110
          },
          "Kalshi": {
            "over": -131,
            "under": 105
          }
        },
        "Freddy Peralta": {
          "k_line": 5.5,
          "Kalshi": {
            "over": -126,
            "under": 105
          }
        },
        "Paul Skenes": {
          "k_line": 6.5,
          "BetMGM": {
            "over": -140,
            "under": 105
          },
          "Kalshi": {
            "over": -121,
            "under": 101
          }
        },
        "Chris Bassitt": {
          "k_line": 3.5,
          "Kalshi": {
            "over": -175,
            "under": 124
          }
        },
        "Michael Lorenzen": {
          "k_line": 4.5,
          "BetMGM": {
            "over": 110,
            "under": -150
          },
          "Kalshi": {
            "over": 119,
            "under": -161
          }
        },
        "Jeffrey Springs": {
          "k_line": 3.5,
          "BetMGM": {
            "over": -175,
            "under": 130
          }
        },
        "Bailey Ober": {
          "k_line": 3.5,
          "BetMGM": {
            "over": -165,
            "under": 125
          },
          "Kalshi": {
            "over": -154,
            "under": 124
          }
        },
        "Kevin Gausman": {
          "k_line": 5.5,
          "BetMGM": {
            "over": 105,
            "under": -140
          },
          "Kalshi": {
            "over": 119,
            "under": -142
          }
        }
      }
    },
    {
      "t": "2026-04-30T23:03:57Z",
      "pitchers": {
        "Cristopher Sanchez": {
          "k_line": 6.5,
          "BetMGM": {
            "over": -105,
            "under": -125
          },
          "Kalshi": {
            "over": 119,
            "under": -154
          }
        },
        "Miles Mikolas": {
          "k_line": 3.5,
          "Kalshi": {
            "over": 129,
            "under": -154
          }
        },
        "Paul Skenes": {
          "k_line": 6.5,
          "BetMGM": {
            "over": -140,
            "under": 105
          },
          "Kalshi": {
            "over": -121,
            "under": 101
          }
        },
        "Michael Lorenzen": {
          "k_line": 4.5,
          "BetMGM": {
            "over": 110,
            "under": -150
          },
          "Kalshi": {
            "over": 119,
            "under": -161
          }
        },
        "Chris Bassitt": {
          "k_line": 3.5,
          "Kalshi": {
            "over": -175,
            "under": 124
          }
        },
        "Brandon Woodruff": {
          "k_line": 4.5,
          "Kalshi": {
            "over": -154,
            "under": 124
          }
        },
        "Bryce Elder": {
          "k_line": 4.5,
          "BetMGM": {
            "over": -150,
            "under": 110
          },
          "Kalshi": {
            "over": -131,
            "under": 105
          }
        },
        "Noah Cameron": {
          "k_line": 4.5,
          "BetMGM": {
            "over": -115,
            "under": -115
          }
        },
        "Michael Soroka": {
          "k_line": 5.5,
          "BetMGM": {
            "over": -135,
            "under": 100
          },
          "Kalshi": {
            "over": -131,
            "under": 105
          }
        },
        "Freddy Peralta": {
          "k_line": 5.5,
          "Kalshi": {
            "over": -126,
            "under": 105
          }
        },
        "Jeffrey Springs": {
          "k_line": 3.5,
          "BetMGM": {
            "over": -175,
            "under": 130
          }
        },
        "Logan Webb": {
          "k_line": 5.5,
          "BetMGM": {
            "over": 115,
            "under": -155
          },
          "Kalshi": {
            "over": 105,
            "under": -137
          }
        },
        "Hunter Dobbins": {
          "k_line": 3.5,
          "BetMGM": {
            "over": -115,
            "under": -115
          },
          "Kalshi": {
            "over": -112,
            "under": -107
          }
        },
        "Peter Lambert": {
          "k_line": 5.5,
          "BetMGM": {
            "over": 120,
            "under": -160
          },
          "Kalshi": {
            "over": 152,
            "under": -218
          }
        },
        "Andrew Abbott": {
          "k_line": 4.5,
          "BetMGM": {
            "over": -160,
            "under": 120
          }
        },
        "Framber Valdez": {
          "k_line": 4.5,
          "BetMGM": {
            "over": -110,
            "under": -120
          },
          "Kalshi": {
            "over": -107,
            "under": -112
          }
        },
        "Bailey Ober": {
          "k_line": 3.5,
          "BetMGM": {
            "over": -165,
            "under": 125
          },
          "Kalshi": {
            "over": -154,
            "under": 129
          }
        },
        "Kevin Gausman": {
          "k_line": 5.5,
          "BetMGM": {
            "over": 105,
            "under": -140
          },
          "Kalshi": {
            "over": 119,
            "under": -142
          }
        }
      }
    },
    {
      "t": "2026-04-30T23:29:27Z",
      "pitchers": {
        "Peter Lambert": {
          "k_line": 5.5,
          "BetMGM": {
            "over": 120,
            "under": -160
          },
          "Kalshi": {
            "over": 152,
            "under": -218
          }
        },
        "Michael Soroka": {
          "k_line": 5.5,
          "BetMGM": {
            "over": -135,
            "under": 100
          },
          "Kalshi": {
            "over": -131,
            "under": 105
          }
        },
        "Andrew Abbott": {
          "k_line": 4.5,
          "BetMGM": {
            "over": -160,
            "under": 120
          }
        },
        "Paul Skenes": {
          "k_line": 6.5,
          "BetMGM": {
            "over": -140,
            "under": 105
          },
          "Kalshi": {
            "over": -121,
            "under": 101
          }
        },
        "Noah Cameron": {
          "k_line": 4.5,
          "BetMGM": {
            "over": -115,
            "under": -115
          }
        },
        "Freddy Peralta": {
          "k_line": 5.5,
          "Kalshi": {
            "over": -126,
            "under": 105
          }
        },
        "Cristopher Sanchez": {
          "k_line": 6.5,
          "BetMGM": {
            "over": -105,
            "under": -125
          },
          "Kalshi": {
            "over": 119,
            "under": -154
          }
        },
        "Jeffrey Springs": {
          "k_line": 3.5,
          "BetMGM": {
            "over": -175,
            "under": 130
          }
        },
        "Framber Valdez": {
          "k_line": 4.5,
          "BetMGM": {
            "over": -110,
            "under": -120
          },
          "Kalshi": {
            "over": -107,
            "under": -112
          }
        },
        "Hunter Dobbins": {
          "k_line": 3.5,
          "BetMGM": {
            "over": -115,
            "under": -115
          },
          "Kalshi": {
            "over": -112,
            "under": -107
          }
        },
        "Miles Mikolas": {
          "k_line": 3.5,
          "Kalshi": {
            "over": 129,
            "under": -154
          }
        },
        "Brandon Woodruff": {
          "k_line": 4.5,
          "Kalshi": {
            "over": -154,
            "under": 124
          }
        },
        "Logan Webb": {
          "k_line": 5.5,
          "BetMGM": {
            "over": 115,
            "under": -155
          },
          "Kalshi": {
            "over": 105,
            "under": -137
          }
        },
        "Bryce Elder": {
          "k_line": 4.5,
          "BetMGM": {
            "over": -150,
            "under": 110
          },
          "Kalshi": {
            "over": -131,
            "under": 105
          }
        },
        "Michael Lorenzen": {
          "k_line": 4.5,
          "BetMGM": {
            "over": 110,
            "under": -150
          },
          "Kalshi": {
            "over": 119,
            "under": -161
          }
        },
        "Chris Bassitt": {
          "k_line": 3.5,
          "Kalshi": {
            "over": -175,
            "under": 124
          }
        },
        "Bailey Ober": {
          "k_line": 3.5,
          "BetMGM": {
            "over": -165,
            "under": 125
          },
          "Kalshi": {
            "over": -154,
            "under": 129
          }
        },
        "Kevin Gausman": {
          "k_line": 5.5,
          "BetMGM": {
            "over": 105,
            "under": -140
          },
          "Kalshi": {
            "over": 119,
            "under": -142
          }
        }
      }
    },
    {
      "t": "2026-04-30T23:59:33Z",
      "pitchers": {
        "Peter Lambert": {
          "k_line": 5.5,
          "BetMGM": {
            "over": 120,
            "under": -160
          },
          "Kalshi": {
            "over": 152,
            "under": -218
          }
        },
        "Paul Skenes": {
          "k_line": 6.5,
          "BetMGM": {
            "over": -140,
            "under": 105
          },
          "Kalshi": {
            "over": -121,
            "under": 101
          }
        },
        "Michael Soroka": {
          "k_line": 5.5,
          "BetMGM": {
            "over": -135,
            "under": 100
          },
          "Kalshi": {
            "over": -131,
            "under": 105
          }
        },
        "Framber Valdez": {
          "k_line": 4.5,
          "BetMGM": {
            "over": -110,
            "under": -120
          },
          "Kalshi": {
            "over": -107,
            "under": -112
          }
        },
        "Brandon Woodruff": {
          "k_line": 4.5,
          "Kalshi": {
            "over": -154,
            "under": 124
          }
        },
        "Andrew Abbott": {
          "k_line": 4.5,
          "BetMGM": {
            "over": -160,
            "under": 120
          }
        },
        "Logan Webb": {
          "k_line": 5.5,
          "BetMGM": {
            "over": 115,
            "under": -155
          },
          "Kalshi": {
            "over": 105,
            "under": -137
          }
        },
        "Miles Mikolas": {
          "k_line": 3.5,
          "Kalshi": {
            "over": 129,
            "under": -154
          }
        },
        "Freddy Peralta": {
          "k_line": 5.5,
          "Kalshi": {
            "over": -126,
            "under": 105
          }
        },
        "Chris Bassitt": {
          "k_line": 3.5,
          "Kalshi": {
            "over": -175,
            "under": 124
          }
        },
        "Michael Lorenzen": {
          "k_line": 4.5,
          "BetMGM": {
            "over": 110,
            "under": -150
          },
          "Kalshi": {
            "over": 119,
            "under": -161
          }
        },
        "Noah Cameron": {
          "k_line": 4.5,
          "BetMGM": {
            "over": -115,
            "under": -115
          }
        },
        "Jeffrey Springs": {
          "k_line": 3.5,
          "BetMGM": {
            "over": -175,
            "under": 130
          }
        },
        "Kevin Gausman": {
          "k_line": 5.5,
          "BetMGM": {
            "over": 105,
            "under": -140
          },
          "Kalshi": {
            "over": 119,
            "under": -142
          }
        },
        "Bryce Elder": {
          "k_line": 4.5,
          "BetMGM": {
            "over": -150,
            "under": 110
          },
          "Kalshi": {
            "over": -131,
            "under": 105
          }
        },
        "Cristopher Sanchez": {
          "k_line": 6.5,
          "BetMGM": {
            "over": -105,
            "under": -125
          },
          "Kalshi": {
            "over": 119,
            "under": -154
          }
        },
        "Hunter Dobbins": {
          "k_line": 3.5,
          "BetMGM": {
            "over": -115,
            "under": -115
          },
          "Kalshi": {
            "over": -112,
            "under": -107
          }
        },
        "Bailey Ober": {
          "k_line": 3.5,
          "BetMGM": {
            "over": -165,
            "under": 125
          },
          "Kalshi": {
            "over": -154,
            "under": 129
          }
        }
      }
    },
    {
      "t": "2026-05-01T01:23:33Z",
      "pitchers": {
        "Freddy Peralta": {
          "k_line": 5.5,
          "Kalshi": {
            "over": -126,
            "under": 105
          }
        },
        "Peter Lambert": {
          "k_line": 5.5,
          "BetMGM": {
            "over": 120,
            "under": -160
          },
          "Kalshi": {
            "over": 152,
            "under": -218
          }
        },
        "Kevin Gausman": {
          "k_line": 5.5,
          "BetMGM": {
            "over": 105,
            "under": -140
          },
          "Kalshi": {
            "over": 119,
            "under": -142
          }
        },
        "Framber Valdez": {
          "k_line": 4.5,
          "BetMGM": {
            "over": -110,
            "under": -120
          },
          "Kalshi": {
            "over": -107,
            "under": -112
          }
        },
        "Paul Skenes": {
          "k_line": 6.5,
          "BetMGM": {
            "over": -140,
            "under": 105
          },
          "Kalshi": {
            "over": -121,
            "under": 101
          }
        },
        "Michael Soroka": {
          "k_line": 5.5,
          "BetMGM": {
            "over": -135,
            "under": 100
          },
          "Kalshi": {
            "over": -131,
            "under": 105
          }
        },
        "Miles Mikolas": {
          "k_line": 3.5,
          "Kalshi": {
            "over": 129,
            "under": -154
          }
        },
        "Bryce Elder": {
          "k_line": 4.5,
          "BetMGM": {
            "over": -150,
            "under": 110
          },
          "Kalshi": {
            "over": -131,
            "under": 105
          }
        },
        "Cristopher Sanchez": {
          "k_line": 6.5,
          "BetMGM": {
            "over": -105,
            "under": -125
          },
          "Kalshi": {
            "over": 119,
            "under": -154
          }
        },
        "Jeffrey Springs": {
          "k_line": 3.5,
          "BetMGM": {
            "over": -175,
            "under": 130
          }
        },
        "Hunter Dobbins": {
          "k_line": 3.5,
          "BetMGM": {
            "over": -115,
            "under": -115
          },
          "Kalshi": {
            "over": -112,
            "under": -107
          }
        },
        "Noah Cameron": {
          "k_line": 4.5,
          "BetMGM": {
            "over": -115,
            "under": -115
          }
        },
        "Brandon Woodruff": {
          "k_line": 4.5,
          "Kalshi": {
            "over": -154,
            "under": 124
          }
        },
        "Michael Lorenzen": {
          "k_line": 4.5,
          "BetMGM": {
            "over": 110,
            "under": -150
          },
          "Kalshi": {
            "over": 119,
            "under": -161
          }
        },
        "Andrew Abbott": {
          "k_line": 4.5,
          "BetMGM": {
            "over": -160,
            "under": 120
          }
        },
        "Bailey Ober": {
          "k_line": 3.5,
          "BetMGM": {
            "over": -165,
            "under": 125
          },
          "Kalshi": {
            "over": -154,
            "under": 129
          }
        },
        "Logan Webb": {
          "k_line": 5.5,
          "BetMGM": {
            "over": 115,
            "under": -155
          },
          "Kalshi": {
            "over": 105,
            "under": -137
          }
        },
        "Chris Bassitt": {
          "k_line": 3.5,
          "Kalshi": {
            "over": -175,
            "under": 124
          }
        }
      }
    },
    {
      "t": "2026-05-01T04:13:22Z",
      "pitchers": {
        "Noah Cameron": {
          "k_line": 4.5,
          "BetMGM": {
            "over": -115,
            "under": -115
          }
        },
        "Kevin Gausman": {
          "k_line": 5.5,
          "BetMGM": {
            "over": 105,
            "under": -140
          },
          "Kalshi": {
            "over": 119,
            "under": -142
          }
        },
        "Bryce Elder": {
          "k_line": 4.5,
          "BetMGM": {
            "over": -150,
            "under": 110
          },
          "Kalshi": {
            "over": -131,
            "under": 105
          }
        },
        "Michael Lorenzen": {
          "k_line": 4.5,
          "BetMGM": {
            "over": 110,
            "under": -150
          },
          "Kalshi": {
            "over": 119,
            "under": -161
          }
        },
        "Bailey Ober": {
          "k_line": 3.5,
          "BetMGM": {
            "over": -165,
            "under": 125
          },
          "Kalshi": {
            "over": -154,
            "under": 129
          }
        },
        "Paul Skenes": {
          "k_line": 6.5,
          "BetMGM": {
            "over": -140,
            "under": 105
          },
          "Kalshi": {
            "over": -121,
            "under": 101
          }
        },
        "Chris Bassitt": {
          "k_line": 3.5,
          "Kalshi": {
            "over": -175,
            "under": 124
          }
        },
        "Peter Lambert": {
          "k_line": 5.5,
          "BetMGM": {
            "over": 120,
            "under": -160
          },
          "Kalshi": {
            "over": 152,
            "under": -218
          }
        },
        "Brandon Woodruff": {
          "k_line": 4.5,
          "Kalshi": {
            "over": -154,
            "under": 124
          }
        },
        "Andrew Abbott": {
          "k_line": 4.5,
          "BetMGM": {
            "over": -160,
            "under": 120
          }
        },
        "Freddy Peralta": {
          "k_line": 5.5,
          "Kalshi": {
            "over": -126,
            "under": 105
          }
        },
        "Miles Mikolas": {
          "k_line": 3.5,
          "Kalshi": {
            "over": 129,
            "under": -154
          }
        },
        "Hunter Dobbins": {
          "k_line": 3.5,
          "BetMGM": {
            "over": -115,
            "under": -115
          },
          "Kalshi": {
            "over": -112,
            "under": -107
          }
        },
        "Jeffrey Springs": {
          "k_line": 3.5,
          "BetMGM": {
            "over": -175,
            "under": 130
          }
        },
        "Michael Soroka": {
          "k_line": 5.5,
          "BetMGM": {
            "over": -135,
            "under": 100
          },
          "Kalshi": {
            "over": -131,
            "under": 105
          }
        },
        "Framber Valdez": {
          "k_line": 4.5,
          "BetMGM": {
            "over": -110,
            "under": -120
          },
          "Kalshi": {
            "over": -107,
            "under": -112
          }
        },
        "Logan Webb": {
          "k_line": 5.5,
          "BetMGM": {
            "over": 115,
            "under": -155
          },
          "Kalshi": {
            "over": 105,
            "under": -137
          }
        },
        "Cristopher Sanchez": {
          "k_line": 6.5,
          "BetMGM": {
            "over": -105,
            "under": -125
          },
          "Kalshi": {
            "over": 119,
            "under": -154
          }
        }
      }
    },
    {
      "t": "2026-05-01T04:38:06Z",
      "pitchers": {
        "Jeffrey Springs": {
          "k_line": 3.5,
          "BetMGM": {
            "over": -175,
            "under": 130
          }
        },
        "Bailey Ober": {
          "k_line": 3.5,
          "BetMGM": {
            "over": -165,
            "under": 125
          },
          "Kalshi": {
            "over": -154,
            "under": 129
          }
        },
        "Freddy Peralta": {
          "k_line": 5.5,
          "Kalshi": {
            "over": -126,
            "under": 105
          }
        },
        "Michael Soroka": {
          "k_line": 5.5,
          "BetMGM": {
            "over": -135,
            "under": 100
          },
          "Kalshi": {
            "over": -131,
            "under": 105
          }
        },
        "Chris Bassitt": {
          "k_line": 3.5,
          "Kalshi": {
            "over": -175,
            "under": 124
          }
        },
        "Miles Mikolas": {
          "k_line": 3.5,
          "Kalshi": {
            "over": 129,
            "under": -154
          }
        },
        "Michael Lorenzen": {
          "k_line": 4.5,
          "BetMGM": {
            "over": 110,
            "under": -150
          },
          "Kalshi": {
            "over": 119,
            "under": -161
          }
        },
        "Logan Webb": {
          "k_line": 5.5,
          "BetMGM": {
            "over": 115,
            "under": -155
          },
          "Kalshi": {
            "over": 105,
            "under": -137
          }
        },
        "Bryce Elder": {
          "k_line": 4.5,
          "BetMGM": {
            "over": -150,
            "under": 110
          },
          "Kalshi": {
            "over": -131,
            "under": 105
          }
        },
        "Peter Lambert": {
          "k_line": 5.5,
          "BetMGM": {
            "over": 120,
            "under": -160
          },
          "Kalshi": {
            "over": 152,
            "under": -218
          }
        },
        "Noah Cameron": {
          "k_line": 4.5,
          "BetMGM": {
            "over": -115,
            "under": -115
          }
        },
        "Framber Valdez": {
          "k_line": 4.5,
          "BetMGM": {
            "over": -110,
            "under": -120
          },
          "Kalshi": {
            "over": -107,
            "under": -112
          }
        },
        "Cristopher Sanchez": {
          "k_line": 6.5,
          "BetMGM": {
            "over": -105,
            "under": -125
          },
          "Kalshi": {
            "over": 119,
            "under": -154
          }
        },
        "Hunter Dobbins": {
          "k_line": 3.5,
          "BetMGM": {
            "over": -115,
            "under": -115
          },
          "Kalshi": {
            "over": -112,
            "under": -107
          }
        },
        "Paul Skenes": {
          "k_line": 6.5,
          "BetMGM": {
            "over": -140,
            "under": 105
          },
          "Kalshi": {
            "over": -121,
            "under": 101
          }
        },
        "Kevin Gausman": {
          "k_line": 5.5,
          "BetMGM": {
            "over": 105,
            "under": -140
          },
          "Kalshi": {
            "over": 119,
            "under": -142
          }
        },
        "Brandon Woodruff": {
          "k_line": 4.5,
          "Kalshi": {
            "over": -154,
            "under": 124
          }
        },
        "Andrew Abbott": {
          "k_line": 4.5,
          "BetMGM": {
            "over": -160,
            "under": 120
          }
        }
      }
    }
  ],
  "archive_dates": [
    "2026-04-30"
  ],
  "updated_at": "2026-05-01T04:38:06Z"
}